README.md
setup.py
Baryonification/__init__.py
Baryonification.egg-info/PKG-INFO
Baryonification.egg-info/SOURCES.txt
Baryonification.egg-info/dependency_links.txt
Baryonification.egg-info/not-zip-safe
Baryonification.egg-info/requires.txt
Baryonification.egg-info/top_level.txt
Baryonification/Profiles/BaryonCorrection.py
Baryonification/Profiles/Battaglia.py
Baryonification/Profiles/Schneider19.py
Baryonification/Profiles/Thermodynamic.py
Baryonification/Profiles/__init__.py
Baryonification/Runners/HealpixRunner.py
Baryonification/Runners/Map2DRunner.py
Baryonification/Runners/SnapshotRunner.py
Baryonification/Runners/__init__.py
Baryonification/utils/Parallelize.py
Baryonification/utils/Pixel.py
Baryonification/utils/Tabulate.py
Baryonification/utils/__init__.py
Baryonification/utils/debug.py
Baryonification/utils/io.py
Baryonification/utils/misc.py