Metadata-Version: 2.1
Name: Baryonification
Version: 0.1.2
Summary: A pipeline for adding baryonic imprints and thermodynamic maps to N-body simulations
Home-page: https://github.com/DhayaaAnbajagane/Baryonification
Author: Dhayaa Anbajagane
Author-email: dhayaa@uchicago.edu
Classifier: Programming Language :: Python :: 3
Classifier: License :: OSI Approved :: MIT License
Classifier: Operating System :: OS Independent
Requires-Python: >=3.6
